wa/__init__.py
wa/_version.py
wa/app.py
wa/extract.py
wa/utils.py
webarchive-0.4.0.data/scripts/webarchive-qt
webarchive-0.4.0.dist-info/LICENSE
webarchive-0.4.0.dist-info/METADATA
webarchive-0.4.0.dist-info/WHEEL
webarchive-0.4.0.dist-info/entry_points.txt
webarchive-0.4.0.dist-info/top_level.txt
webarchive-0.4.0.dist-info/RECORD
