Metadata-Version: 2.1
Name: webarchive
Version: 0.4.0
Summary: Archive web articles
Home-page: https://gitlab.com/mgoral/webarchive
Author: Michał Góral
Author-email: dev@goral.net.pl
License: GPLv3+
Platform: linux
Classifier: Development Status :: 4 - Beta
Classifier: Environment :: Console
Classifier: Intended Audience :: End Users/Desktop
Classifier: License :: OSI Approved :: GNU General Public License v3 or later (GPLv3+)
Classifier: Natural Language :: English
Classifier: Operating System :: POSIX
Classifier: Programming Language :: Python :: 3 :: Only
Classifier: Programming Language :: Python :: 3.7
Classifier: Programming Language :: Python :: 3.8
Classifier: Topic :: Utilities
Requires-Python: >=3.7,<3.9
Requires-Dist: beautifulsoup4 (==4.8.2)
Requires-Dist: chardet (==3.0.4)
Requires-Dist: lxml (==4.5.0)
Requires-Dist: readability-lxml (==0.7.1)
Requires-Dist: requests (==2.23.0)
Provides-Extra: gui
Requires-Dist: PyQt5 ; extra == 'gui'
